Workbook

Sheet Leads
A1: Priority | B1: Company | C1: Segment | D1: Sub-type | E1: Country | F1: City | G1: Email | H1: Email type | I1: Phone | J1: Website | K1: LinkedIn | L1: What they do | M1: Why they fit | N1: Pitch angle | O1: Demo link path (add to your demo URL) | P1: Email source | Q1: Status | R1: Date sent | S1: Notes
A2: A | B2: Dutum Company Limited | C2: Facility management | D2: Integrated FM | E2: Nigeria | F2: Lagos | G2: info@dutumgroup.com | H2: Company inbox | J2: https://dutumgroup.com/ | L2: Construction and facility management firm offering building FM across Nigeria. | M2: Core fit: recurring field maintenance across many sites. Multi-location. | N2: Multi-building portfolio: planned maintenance schedules, technician dispatch and per-building client reporting. | O2: /demo?industry=facilities&client=Dutum%20Company%20Limited | P2: https://dutumgroup.com/contact/ | Q2: Not contacted
A3: A | B3: Elektrint (Nigeria) Limited | C3: Facility management | D3: MEP maintenance | E3: Nigeria | F3: Lagos | G3: elektrintlagos@elektrint.com | H3: Company inbox | I3: +234 9 782 2768 | J3: https://www.elektrint.com/ | K3: https://www.linkedin.com/company/elektrint-nigeria-ltd./ | L3: Electromechanical installation and facility maintenance services, with branches in Lagos, Abuja and Port Harcourt. | M3: Good fit: maintenance work across client sites. Multi-location. | N3: Maintenance contracts across client buildings: work orders, checklists and proof of work per visit. | O3: /demo?industry=facilities&client=Elektrint | P3: https://www.elektrint.com/ | Q3: Not contacted
A4: A | B4: Global Property & Facilities International Ltd (GPFI) | C4: Facility management | D4: Integrated FM | E4: Nigeria | F4: Lagos | G4: bd@globalpfi.com | H4: Company inbox | I4: +234 803 332 7649 | J4: https://gpfi.ng/ | K4: https://www.linkedin.com/company/gpfinigeria | L4: Integrated FM, security and sustainability technology for commercial, residential, healthcare and industrial sites, operating in several African countries. | M4: Core fit: recurring field maintenance across many sites. Multi-location. | N4: Multi-building portfolio: planned maintenance schedules, technician dispatch and per-building client reporting. | O4: /demo?industry=facilities&client=Global%20Property%20%26%20Facilities%20International%20Ltd | P4: https://gpfi.ng/ | Q4: Not contacted
A5: A | B5: Jide Taiwo & Co. | C5: Facility management | D5: Property / estate FM | E5: Nigeria | F5: Lagos | G5: info@jidetaiwoandco.com | H5: Company inbox | J5: https://jidetaiwoandco.com/ | L5: Estate surveying firm with a nationwide facility and property management division for residential, commercial and retail buildings. | M5: Good fit: maintenance work across client sites. Multi-location. | N5: Tenant requests become tracked work orders with technician dispatch and landlord reporting. | O5: /demo?industry=facilities&client=Jide%20Taiwo%20%26%20Co. | P5: https://jidetaiwoandco.com/contact.php | Q5: Not contacted
A6: A | B6: Kleenol Nigeria Limited | C6: Facility management | D6: HVAC maintenance | E6: Nigeria | F6: Lagos | G6: kleenol@yahoo.co.uk | H6: Free-mail inbox | I6: +234 803 506 6601 | J6: https://www.kleenolng.com/ | K6: https://www.linkedin.com/company/kleenol-nigeria-professional-cleaning-services-company/ | L6: FM covering electrical, plumbing, HVAC and generator maintenance (2.5 kVA to 2,500 kVA) as well as cleaning; offices in Lagos and Abuja. | M6: Good fit: maintenance work across client sites. Multi-location. | N6: Annual maintenance contracts: never miss a scheduled service, photo proof for every visit. | O6: /demo?industry=facilities&client=Kleenol%20Nigeria%20Limited | P6: https://www.kleenolng.com/ | Q6: Not contacted
A7: A | B7: Kresta Laurel Limited | C7: Facility management | D7: Lifts & escalators | E7: Nigeria | F7: Lagos | G7: kresta@krestalaurel.com | H7: Company inbox | I7: 08037959341 | J7: https://krestalaurel.com/ | K7: https://www.linkedin.com/company/kresta-laurel-limited/ | L7: Elevators, escalators, generators, UPS and engineering services, with branches in Lagos, Abuja, Port Harcourt, Ibadan and Uyo. | M7: Lifts, generators and UPS with five branches. | N7: Entrapment callouts and statutory inspections: response-time SLAs and inspection records per lift. | O7: /demo?industry=facilities&client=Kresta%20Laurel%20Limited | P7: https://krestalaurel.com/ | Q7: Not contacted
A8: A | B8: Lift Elevator Craft | C8: Facility management | D8: Lifts & escalators | E8: Nigeria | F8: Lagos | G8: info@liftelevator.com.ng | H8: Company inbox | I8: +234 802 751 8309 | J8: https://www.liftelevator.com.ng/ | L8: Elevator repair, maintenance and installation for commercial and residential buildings in Lagos, Abuja and Anambra. | M8: Core fit: recurring field maintenance across many sites. Multi-location. | N8: Entrapment callouts and statutory inspections: response-time SLAs and inspection records per lift. | O8: /demo?industry=facilities&client=Lift%20Elevator%20Craft | P8: https://www.liftelevator.com.ng/ | Q8: Not contacted
A9: A | B9: Orakl Solutions | C9: Facility management | D9: Lifts & escalators | E9: Nigeria | F9: Lagos | G9: hello@orakl-solutions.com | H9: Company inbox | I9: +234 913 333 3989 | J9: https://orakl-solutions.com/ | K9: https://www.linkedin.com/company/orakl-solutions/ | L9: Elevator and escalator installation and maintenance, with offices in Lagos, Abuja and Port Harcourt. | M9: Core fit: recurring field maintenance across many sites. Multi-location. | N9: Entrapment callouts and statutory inspections: response-time SLAs and inspection records per lift. | O9: /demo?industry=facilities&client=Orakl%20Solutions | P9: https://orakl-solutions.com/ | Q9: Not contacted
A10: A | B10: Sarakeys | C10: Facility management | D10: Lifts & escalators | E10: Nigeria | F10: Ota | G10: info@sarakeys.com.ng | H10: Company inbox | I10: +234 909 971 7070 | J10: http://www.sarakeys.com.ng/ | L10: Elevator and escalator sales, installation and servicing for commercial and residential buildings. | M10: Core fit: recurring field maintenance across many sites. | N10: Entrapment callouts and statutory inspections: response-time SLAs and inspection records per lift. | O10: /demo?industry=facilities&client=Sarakeys | P10: http://www.sarakeys.com.ng/ | Q10: Not contacted
A11: A | B11: Solid Rock Facility Managers | C11: Facility management | D11: Integrated FM | E11: Nigeria | F11: Lagos | G11: info@solidrockfacilitymanagers.com | H11: Company inbox | I11: +234 706 448 7048 | J11: http://solidrockfacilitymanagers.com/ | L11: Maintenance and facility management services since 2008, with offices in Lagos, Port Harcourt, Abuja and Ilorin. | M11: Core fit: recurring field maintenance across many sites. Multi-location. | N11: Multi-building portfolio: planned maintenance schedules, technician dispatch and per-building client reporting. | O11: /demo?industry=facilities&client=Solid%20Rock%20Facility%20Managers | P11: http://solidrockfacilitymanagers.com/ | Q11: Not contacted
A12: A | B12: Tecnicool Nigeria Limited | C12: Facility management | D12: HVAC maintenance | E12: Nigeria | F12: Lagos | G12: info@tecnicoolnig.com | H12: Company inbox | I12: 08098899935 | J12: https://tecnicoolnig.com/ | L12: Commercial HVAC sales, installation and maintenance with offices in Lagos, Abuja, Ilorin and Kaduna. | M12: Good fit: maintenance work across client sites. Multi-location. | N12: Annual maintenance contracts: never miss a scheduled service, photo proof for every visit. | O12: /demo?industry=facilities&client=Tecnicool%20Nigeria%20Limited | P12: https://tecnicoolnig.com/ | Q12: Not contacted
A13: A | B13: Ashipa Electric Limited | C13: Solar | D13: Mini-grid developer/operator | E13: Nigeria | F13: Abuja | G13: info@ashipaelectric.com | H13: Company inbox | J13: https://www.ashipaelectric.com | K13: https://www.linkedin.com/company/ashipaelectric/ | L13: Solar, storage, microgrid and EPC services in West Africa and North America; West Africa office in Garki, Abuja | M13: Core fit: recurring field maintenance across many sites. | N13: Many remote sites and funder/lender reporting (DARES, AMDA etc.): GPS-verified O&M visits and photo evidence financiers trust. | O13: /demo?industry=solar&client=Ashipa%20Electric%20Limited | P13: https://www.ashipaelectric.com | Q13: Not contacted
A14: A | B14: DB Energy | C14: Solar | D14: C&I solar / EPC | E14: Nigeria | F14: Asaba | G14: info@dbenergy.com.ng | H14: Company inbox | I14: +234 706 514 9178 | J14: https://www.dbenergy.ng | K14: https://linkedin.com/company/dbenergy | L14: Residential and C&I solar installation and maintenance (5MW installed) in Lagos, Abuja, Port Harcourt, Enugu, Benin and Asaba | M14: Good fit: maintenance work across client sites. Multi-location. | N14: Turn one-off installs into recurring maintenance contracts: scheduled PM per site and client-facing service reports. | O14: /demo?industry=solar&client=DB%20Energy | P14: https://www.dbenergy.ng | Q14: Not contacted
A15: A | B15: Darway Coast Ltd | C15: Solar | D15: Mini-grid developer/operator | E15: Nigeria | F15: Abuja | G15: support@darwaycoast.com | H15: Company inbox | I15: 0803 3889 202 | J15: https://darwaycoast.com | K15: https://www.linkedin.com/company/darway-coast-ltd | L15: Mini-grid developer with 30+ solar mini-grids (~3.5MW) across 8 states and offices in Abuja, Lagos and Owerri; DARES grantee | M15: Core fit: recurring field maintenance across many sites. Multi-location. | N15: Many remote sites and funder/lender reporting (DARES, AMDA etc.): GPS-verified O&M visits and photo evidence financiers trust. | O15: /demo?industry=solar&client=Darway%20Coast%20Ltd | P15: https://darwaycoast.com | Q15: Not contacted
A16: A | B16: EM-ONE Energy Solutions | C16: Solar | D16: Mini-grid developer/operator | E16: Nigeria | F16: Abuja | G16: info@emone.energy | H16: Company inbox | J16: https://www.emone.energy | K16: https://ca.linkedin.com/company/em-one-energy | L16: Solar microgrid EPC (3.1MW University of Abuja, 1MW Kano interconnected mini-grid); global HQ in Abuja | M16: Core fit: recurring field maintenance across many sites. | N16: Many remote sites and funder/lender reporting (DARES, AMDA etc.): GPS-verified O&M visits and photo evidence financiers trust. | O16: /demo?industry=solar&client=EM-ONE%20Energy%20Solutions | P16: https://www.emone.energy | Q16: Not contacted
A17: A | B17: EtinPower Limited | C17: Solar | D17: Mini-grid developer/operator | E17: Nigeria | F17: Benin City | G17: info@etinpower.com | H17: Company inbox | I17: +234 903 175 1422 | J17: https://www.etinpower.com | K17: https://linkedin.com/company/etinpowerlimited | L17: Solar mini-grid developer and operator for off-grid communities (e.g. Gbelebu, Edo State); AMDA member | M17: Core fit: recurring field maintenance across many sites. | N17: Many remote sites and funder/lender reporting (DARES, AMDA etc.): GPS-verified O&M visits and photo evidence financiers trust. | O17: /demo?industry=solar&client=EtinPower%20Limited | P17: https://www.etinpower.com | Q17: Not contacted
A18: A | B18: Greenage Technologies Power Systems | C18: Solar | D18: Mini-grid developer/operator | E18: Nigeria | F18: Enugu | G18: contact@greenagetech.com | H18: Company inbox | J18: https://greenagetech.com | K18: https://ng.linkedin.com/company/greenage-technologies | L18: Mini-grids, solar installation and engineering, plus its own inverter line (3.5-20KVA) | M18: Core fit: recurring field maintenance across many sites. | N18: Many remote sites and funder/lender reporting (DARES, AMDA etc.): GPS-verified O&M visits and photo evidence financiers trust. | O18: /demo?industry=solar&client=Greenage%20Technologies%20Power%20Systems | P18: https://greenagetech.com/contact-us/ | Q18: Not contacted
A19: A | B19: Havenhill Synergy Ltd | C19: Solar | D19: Mini-grid developer/operator | E19: Nigeria | F19: Abuja | G19: info@havenhillsynergy.com | H19: Company inbox | I19: +2347063803881 | J19: https://havenhillsynergy.com | K19: https://www.linkedin.com/company/havenhill-synergy/ | L19: Clean-tech utility running rural solar mini-grids plus commercial and healthcare solar electrification; received IMAS mini-grid grants | M19: Core fit: recurring field maintenance across many sites. | N19: Many remote sites and funder/lender reporting (DARES, AMDA etc.): GPS-verified O&M visits and photo evidence financiers trust. | O19: /demo?industry=solar&client=Havenhill%20Synergy%20Ltd | P19: https://havenhillsynergy.com | Q19: Not contacted
A20: A | B20: Indicel Solar | C20: Solar | D20: C&I solar / EPC | E20: Nigeria | F20: Enugu | G20: info@indicelsolar.com | H20: Company inbox | I20: +2348108497593 | J20: https://indicelsolar.com | L20: Residential, hybrid and large-scale solar installation and servicing since 2009; offices in Enugu, Abuja and Asaba | M20: Good fit: maintenance work across client sites. Multi-location. | N20: Turn one-off installs into recurring maintenance contracts: scheduled PM per site and client-facing service reports. | O20: /demo?industry=solar&client=Indicel%20Solar | P20: https://indicelsolar.com/contact.php | Q20: Not contacted
A21: A | B21: Prado Power | C21: Solar | D21: Mini-grid developer/operator | E21: Nigeria | F21: Abuja | G21: info@pradopower.org | H21: Company inbox | I21: +234 808 220 9245 | J21: https://www.pradopower.org | K21: https://www.linkedin.com/company/11107148 | L21: Microgrids, solar installations and energy management for off-grid and underserved communities | M21: Core fit: recurring field maintenance across many sites. | N21: Many remote sites and funder/lender reporting (DARES, AMDA etc.): GPS-verified O&M visits and photo evidence financiers trust. | O21: /demo?industry=solar&client=Prado%20Power | P21: https://www.pradopower.org | Q21: Not contacted
A22: A | B22: PriVida Power Limited | C22: Solar | D22: Mini-grid developer/operator | E22: Nigeria | F22: Lagos | G22: info@prividaenergy.com | H22: Company inbox | I22: +441919085632 | J22: https://www.prividaenergy.com | K22: https://www.linkedin.com/company/privida-energy | L22: Mini-grid developer (DARES/NEP grantee, rolling out in 25 communities); Lagos office plus UK office | M22: Core fit: recurring field maintenance across many sites. | N22: Many remote sites and funder/lender reporting (DARES, AMDA etc.): GPS-verified O&M visits and photo evidence financiers trust. | O22: /demo?industry=solar&client=PriVida%20Power%20Limited | P22: https://www.prividaenergy.com | Q22: Not contacted
A23: A | B23: Protergia Energy Nigeria | C23: Solar | D23: Mini-grid developer/operator | E23: Nigeria | F23: Abuja | G23: info@protergiaenergy.com | H23: Company inbox | I23: +234 806 998 3828 | J23: https://protergiaenergy.com | K23: https://www.linkedin.com/company/protergiaenergy/ | L23: Clean-energy utility and mini-grid developer for underserved communities; DARES mini-grid grantee | M23: Core fit: recurring field maintenance across many sites. | N23: Many remote sites and funder/lender reporting (DARES, AMDA etc.): GPS-verified O&M visits and photo evidence financiers trust. | O23: /demo?industry=solar&client=Protergia%20Energy%20Nigeria | P23: https://protergiaenergy.com | Q23: Not contacted
A24: A | B24: Rubitec Solar | C24: Solar | D24: Mini-grid developer/operator | E24: Nigeria | F24: Lagos | G24: info@rubitecsolar.com | H24: Company inbox | I24: +2347087054296 | J24: https://rubitecsolar.com | L24: Installs and maintains solar, inverter backup and small hydro/biomass systems, and develops mini-grid electrification projects; IMAS grantee | M24: Core fit: recurring field maintenance across many sites. | N24: Many remote sites and funder/lender reporting (DARES, AMDA etc.): GPS-verified O&M visits and photo evidence financiers trust. | O24: /demo?industry=solar&client=Rubitec%20Solar | P24: https://rubitecsolar.com | Q24: Not contacted
A25: A | B25: Solarlify | C25: Solar | D25: Residential & small commercial installer | E25: Nigeria | F25: Lagos | G25: admin@solarlify.com.ng | H25: Company inbox | I25: 090-240-224-84 | J25: https://solarlify.com.ng | L25: Solar and inverter installation, repair and maintenance; 1,275+ customers and 20+ branches across 7 states | M25: 20+ branches and a service/repair business: dispatch pain. | N25: High volume of service calls across many homes: dispatch the nearest technician and track repeat faults. | O25: /demo?industry=solar&client=Solarlify | P25: https://solarlify.com.ng | Q25: Not contacted
A26: A | B26: Sosai Renewable Energies Company | C26: Solar | D26: Mini-grid developer/operator | E26: Nigeria | F26: Kaduna | G26: sosai@sosairen.org | H26: Company inbox | I26: +234 809 230 5719 | J26: https://sosairen.org | K26: https://www.linkedin.com/company/sosai-renewable-energies-company/ | L26: Mini-grid and household solar developer with offices in Kaduna and Abuja; IMAS grantee | M26: Core fit: recurring field maintenance across many sites. Multi-location. | N26: Many remote sites and funder/lender reporting (DARES, AMDA etc.): GPS-verified O&M visits and photo evidence financiers trust. | O26: /demo?industry=solar&client=Sosai%20Renewable%20Energies%20Company | P26: https://sosairen.org/contact-us/ | Q26: Not contacted
A27: A | B27: Sunhive Limited | C27: Solar | D27: Mini-grid developer/operator | E27: Nigeria | F27: Lagos | G27: info@sunhive.com | H27: Company inbox | I27: +234 806 456 5176 | J27: https://sunhive.com | K27: https://www.linkedin.com/company/sunhive-ltd/ | L27: Solar EPC with 10MWp+ delivered, plus mini-grids and battery storage; hubs in Lagos and Kano | M27: Core fit: recurring field maintenance across many sites. | N27: Many remote sites and funder/lender reporting (DARES, AMDA etc.): GPS-verified O&M visits and photo evidence financiers trust. | O27: /demo?industry=solar&client=Sunhive%20Limited | P27: https://sunhive.com | Q27: Not contacted
A28: A | B28: CETECH Ghana | C28: Facility management | D28: HVAC maintenance | E28: Ghana | G28: support@cetechbpa.com | H28: Company inbox | I28: +233539003030 | J28: https://cetechbpa.com/ | L28: HVAC/R design, installation, maintenance and repair for residential, commercial and industrial clients across Ghana. | M28: Good fit: maintenance work across client sites. Multi-location. | N28: Annual maintenance contracts: never miss a scheduled service, photo proof for every visit. | O28: /demo?industry=facilities&client=CETECH%20Ghana | P28: https://cetechbpa.com/gh/contact-us/ | Q28: Not contacted
A29: A | B29: Diamond Maintenance Tanzania Limited | C29: Facility management | D29: Integrated FM | E29: Tanzania | F29: Dar es Salaam | G29: info@dm.co.tz | H29: Company inbox | I29: +255 745 406484 | J29: https://dm.co.tz/ | K29: https://www.linkedin.com/company/dmtl-africa | L29: Integrated FM company providing property maintenance, technical services, renovation and sanitation across Tanzania. | M29: Core fit: recurring field maintenance across many sites. Multi-location. | N29: Multi-building portfolio: planned maintenance schedules, technician dispatch and per-building client reporting. | O29: /demo?industry=facilities&client=Diamond%20Maintenance%20Tanzania%20Limited | P29: https://dm.co.tz/ | Q29: Not contacted
A30: A | B30: Elevator Maintenance Company (EMC) | C30: Facility management | D30: Lifts & escalators | E30: South Africa | F30: Pretoria | G30: sales@elevatorcompany.co.za | H30: Company inbox | I30: 012 377 0606 | J30: https://elevatorcompany.co.za/ | K30: https://www.linkedin.com/company/elevator-maintenance-company/ | L30: Multi-brand lift and elevator maintenance, repair, installation and modernisation across South Africa. | M30: Core fit: recurring field maintenance across many sites. Multi-location. | N30: Entrapment callouts and statutory inspections: response-time SLAs and inspection records per lift. | O30: /demo?industry=facilities&client=Elevator%20Maintenance%20Company | P30: https://elevatorcompany.co.za/ | Q30: Not contacted
A31: A | B31: Facilities Management Solutions (FM Solutions) | C31: Facility management | D31: Integrated FM | E31: South Africa | F31: Cape Town | G31: info@fm-solutions.co.za | H31: Company inbox | I31: 086 002 2175 | J31: https://www.fm-solutions.co.za/ | K31: https://www.linkedin.com/company/afroteq-fm-solutions | L31: Integrated technical and soft-services FM provider (part of AFMS Group) doing preventive, corrective and emergency repairs, with offices in Cape Town, Midrand, eThekwini, Gqeberha and Gaborone. | M31: Multi-office technical FM with emergency repairs. | N31: Multi-building portfolio: planned maintenance schedules, technician dispatch and per-building client reporting. | O31: /demo?industry=facilities&client=Facilities%20Management%20Solutions | P31: https://www.fm-solutions.co.za/ | Q31: Not contacted
A32: A | B32: Gamma Heights Engineering | C32: Facility management | D32: Lifts & escalators | E32: Ghana | F32: Accra | G32: sales@gammaheightseng.com | H32: Company inbox | I32: +233 24 438 8165 | J32: https://gammaheightseng.com/ | L32: Supply, installation and maintenance of elevators, escalators, moving walkways and dumbwaiters. | M32: Core fit: recurring field maintenance across many sites. | N32: Entrapment callouts and statutory inspections: response-time SLAs and inspection records per lift. | O32: /demo?industry=facilities&client=Gamma%20Heights%20Engineering | P32: https://gammaheightseng.com/Contact | Q32: Not contacted
A33: A | B33: LeafySpace (Pty) Ltd | C33: Facility management | D33: Integrated FM | E33: South Africa | F33: Kempton Park | G33: info@leafyspace.co.za | H33: Company inbox | I33: +27 11 028 7635 | J33: https://leafyspace.co.za/ | K33: https://www.linkedin.com/company/leafyspace/ | L33: Facilities management provider covering building management, maintenance, electrical, plumbing and cleaning across South Africa. | M33: Core fit: recurring field maintenance across many sites. Multi-location. | N33: Multi-building portfolio: planned maintenance schedules, technician dispatch and per-building client reporting. | O33: /demo?industry=facilities&client=LeafySpace | P33: https://leafyspace.co.za/ | Q33: Not contacted
A34: A | B34: M-Cool Electro Engineering Services Limited | C34: Facility management | D34: HVAC maintenance | E34: Kenya | F34: Nairobi | G34: mcoolelectroengineeringlimited@gmail.com | H34: Free-mail inbox | I34: +254 723 428 167 | J34: https://mcool.co.ke/ | L34: Commercial HVAC, air conditioning, cold room, refrigeration and mechanical ventilation installation and maintenance across Kenya. | M34: Good fit: maintenance work across client sites. Multi-location. | N34: Annual maintenance contracts: never miss a scheduled service, photo proof for every visit. | O34: /demo?industry=facilities&client=M-Cool%20Electro%20Engineering%20Services%20Limited | P34: https://mcool.co.ke/ | Q34: Not contacted
A35: A | B35: Musandah Assets Management | C35: Facility management | D35: Integrated FM | E35: Egypt | G35: info@musandahfm.com | H35: Company inbox | J35: https://musandahfm.com/ | K35: https://www.linkedin.com/company/musandahassetsandfm/ | L35: Egyptian integrated FM provider focused on MEP maintenance and asset management nationwide. | M35: Core fit: recurring field maintenance across many sites. Multi-location. | N35: Multi-building portfolio: planned maintenance schedules, technician dispatch and per-building client reporting. | O35: /demo?industry=facilities&client=Musandah%20Assets%20Management | P35: https://musandahfm.com/contact/ | Q35: Not contacted
A36: A | B36: PKBA Engineering Co | C36: Facility management | D36: HVAC maintenance | E36: Ghana | F36: Accra | G36: info@pkbaengineeringco.com | H36: Company inbox | I36: +233 261609308 | J36: https://pkbaengineeringco.com/ | L36: Air conditioning installation and repair, ventilation, electrical and plumbing services across Ghana. | M36: Good fit: maintenance work across client sites. Multi-location. | N36: Annual maintenance contracts: never miss a scheduled service, photo proof for every visit. | O36: /demo?industry=facilities&client=PKBA%20Engineering%20Co | P36: https://pkbaengineeringco.com/ | Q36: Not contacted
A37: A | B37: Relis Lifts | C37: Facility management | D37: Lifts & escalators | E37: South Africa | F37: Midrand | G37: info@relislifts.co.za | H37: Company inbox | I37: +27 11 733 4033 | J37: https://relislifts.co.za/ | L37: Lift and escalator company doing installation, maintenance, repair, modernisation and 24-hour emergency callouts across South Africa. | M37: Core fit: recurring field maintenance across many sites. Multi-location. | N37: Entrapment callouts and statutory inspections: response-time SLAs and inspection records per lift. | O37: /demo?industry=facilities&client=Relis%20Lifts | P37: https://relislifts.co.za/ | Q37: Not contacted
A38: A | B38: Rise Elevators | C38: Facility management | D38: Lifts & escalators | E38: South Africa | G38: sales@riseelevators.co.za | H38: Company inbox | I38: +27 839 381 676 | J38: https://www.riseelevators.co.za/ | L38: Lift and escalator installation, maintenance, repairs, modernisation and safety inspections, with committed emergency response times. | M38: Core fit: recurring field maintenance across many sites. | N38: Entrapment callouts and statutory inspections: response-time SLAs and inspection records per lift. | O38: /demo?industry=facilities&client=Rise%20Elevators | P38: https://www.riseelevators.co.za/contact | Q38: Not contacted
A39: A | B39: SPINX (SPXSA) | C39: Facility management | D39: Property / estate FM | E39: South Africa | F39: Cape Town | G39: fs@spxsa.com | H39: Company inbox | I39: 087 550 0942 | J39: https://spxsa.com/ | L39: National commercial property maintenance firm with 24/7 response, planned maintenance, refurbishments and technical projects across Cape Town, Johannesburg, Pretoria, Durban, Gqeberha and East London. | M39: National 24/7 maintenance across six cities: core fit. | N39: Tenant requests become tracked work orders with technician dispatch and landlord reporting. | O39: /demo?industry=facilities&client=SPINX | P39: https://spxsa.com/ | Q39: Not contacted
A40: A | B40: ARC Power Ltd | C40: Solar | D40: Mini-grid developer/operator | E40: Rwanda | G40: info@arcpower.co | H40: Company inbox | I40: +250 787 372 047 | J40: https://arcpower.co/ | K40: https://www.linkedin.com/company/arc-power-rw/ | L40: Solar mini-grid developer and operator with offices in Rwanda, Zambia and Mozambique. | M40: Core fit: recurring field maintenance across many sites. Multi-location. | N40: Many remote sites and funder/lender reporting (DARES, AMDA etc.): GPS-verified O&M visits and photo evidence financiers trust. | O40: /demo?industry=solar&client=ARC%20Power%20Ltd | P40: https://arcpower.co/ | Q40: Not contacted
A41: A | B41: Ariya Finergy | C41: Solar | D41: Solar O&M | E41: Kenya | F41: Nairobi | G41: info@ariyafinergy.com | H41: Company inbox | I41: +254 700 784330 | J41: https://ariyafinergy.com/ | K41: https://www.linkedin.com/company/ariya-finergy | L41: Designs, finances, builds and runs O&M for industrial solar, battery storage and power stabilisation projects in Kenya, Tanzania and Uganda. | M41: Runs O&M for industrial solar across East Africa. | N41: O&M contracts depend on response time and proof of work: SLA tracking, verified site visits, client reports. | O41: /demo?industry=solar&client=Ariya%20Finergy | P41: https://ariyafinergy.com/ | Q41: Not contacted
A42: A | B42: Energy Partners | C42: Solar | D42: C&I solar / EPC | E42: South Africa | F42: Cape Town | G42: info@energypartners.co.za | H42: Company inbox | I42: +27 21 941 5140 | J42: https://energypartners.co.za/ | K42: https://za.linkedin.com/company/energy-partners- | L42: Energy solutions for businesses (solar power, refrigeration, steam) with several regional branches. | M42: Good fit: maintenance work across client sites. Multi-location. | N42: Turn one-off installs into recurring maintenance contracts: scheduled PM per site and client-facing service reports. | O42: /demo?industry=solar&client=Energy%20Partners | P42: https://energypartners.co.za/ | Q42: Not contacted
A43: A | B43: Ensol (T) Limited | C43: Solar | D43: Mini-grid developer/operator | E43: Tanzania | F43: Dar es Salaam | G43: info@ensol.co.tz | H43: Company inbox | I43: 0766 694 413 | J43: https://ensol.co.tz/ | K43: https://www.linkedin.com/company/ensol-tanzania-limited | L43: Tanzanian-owned electrical and solar EPC contractor and mini-grid developer working across East Africa. | M43: Core fit: recurring field maintenance across many sites. Multi-location. | N43: Many remote sites and funder/lender reporting (DARES, AMDA etc.): GPS-verified O&M visits and photo evidence financiers trust. | O43: /demo?industry=solar&client=Ensol | P43: https://ensol.co.tz/ | Q43: Not contacted
A44: A | B44: Equator Energy Ltd | C44: Solar | D44: Solar O&M | E44: Kenya | F44: Nairobi | G44: mail@equator.energy | H44: Company inbox | I44: +254 741 879 815 | J44: https://equator.energy/ | L44: C&I solar provider on a pay-per-kWh model for tea factories and industry, with in-house O&M teams across Kenya, Uganda and Senegal. | M44: In-house O&M teams across three countries: core fit. | N44: O&M contracts depend on response time and proof of work: SLA tracking, verified site visits, client reports. | O44: /demo?industry=solar&client=Equator%20Energy%20Ltd | P44: https://equator.energy/ | Q44: Not contacted
A45: A | B45: Forest Energy | C45: Solar | D45: Solar O&M | E45: South Africa | F45: Cape Town | G45: sales@forestenergy.co.za | H45: Company inbox | I45: +27 21 745 9906 | J45: https://www.forestenergy.co.za/ | K45: https://www.linkedin.com/company/forestenergysolutions/ | L45: Commercial solar and battery storage installer with O&M services; offices in Cape Town and Centurion. | M45: C&I installer with an O&M service line. | N45: O&M contracts depend on response time and proof of work: SLA tracking, verified site visits, client reports. | O45: /demo?industry=solar&client=Forest%20Energy | P45: https://www.forestenergy.co.za/ | Q45: Not contacted
A46: A | B46: Jumeme Rural Power Supply | C46: Solar | D46: Mini-grid developer/operator | E46: Tanzania | F46: Mwanza | G46: info@jumeme.com | H46: Company inbox | I46: +255 769 486 844 | J46: https://www.jumeme.com/ | L46: Runs solar-battery-diesel hybrid mini-grids serving rural Tanzanian growth centres. | M46: Core fit: recurring field maintenance across many sites. | N46: Many remote sites and funder/lender reporting (DARES, AMDA etc.): GPS-verified O&M visits and photo evidence financiers trust. | O46: /demo?industry=solar&client=Jumeme%20Rural%20Power%20Supply | P46: https://www.jumeme.com/ | Q46: Not contacted
A47: A | B47: Muhanya Solar Limited | C47: Solar | D47: Mini-grid developer/operator | E47: Zambia | F47: Lusaka | G47: sales@muhanyasolar.com | H47: Company inbox | I47: +260 770 612 225 | J47: https://www.muhanyasolar.com/ | L47: EPC for solar, battery storage, hybrid, mini-grid and water-pumping systems across Zambia. | M47: Core fit: recurring field maintenance across many sites. Multi-location. | N47: Many remote sites and funder/lender reporting (DARES, AMDA etc.): GPS-verified O&M visits and photo evidence financiers trust. | O47: /demo?industry=solar&client=Muhanya%20Solar%20Limited | P47: https://www.muhanyasolar.com/ | Q47: Not contacted
A48: A | B48: New Southern Energy (NSE) | C48: Solar | D48: Solar O&M | E48: South Africa | F48: Cape Town | G48: info@newsouthernenergy.com | H48: Company inbox | I48: (021) 788 1080 | J48: https://www.nse.africa/ | K48: https://www.linkedin.com/company/new-southern-energy/ | L48: Vertically integrated IPP that designs, builds, operates and maintains renewable assets; offices in Cape Town, Johannesburg and Nairobi. | M48: Core fit: recurring field maintenance across many sites. Multi-location. | N48: O&M contracts depend on response time and proof of work: SLA tracking, verified site visits, client reports. | O48: /demo?industry=solar&client=New%20Southern%20Energy | P48: https://www.nse.africa/ | Q48: Not contacted
A49: A | B49: PowerGen Renewable Energy | C49: Solar | D49: Mini-grid developer/operator | E49: Kenya | G49: info@powergen-re.com | H49: Company inbox | J49: https://powergen-renewable-energy.com/ | L49: Solar and battery developer for businesses and mini-grid communities, with operations in Kenya, DRC, Nigeria and Sierra Leone. | M49: Core fit: recurring field maintenance across many sites. | N49: Many remote sites and funder/lender reporting (DARES, AMDA etc.): GPS-verified O&M visits and photo evidence financiers trust. | O49: /demo?industry=solar&client=PowerGen%20Renewable%20Energy | P49: https://powergen-renewable-energy.com/ | Q49: Not contacted
A50: A | B50: PowerHut Renewables Limited | C50: Solar | D50: Mini-grid developer/operator | E50: Tanzania | F50: Arusha | G50: info@powerhut.co.tz | H50: Company inbox | I50: +255 762 508 917 | J50: https://powerhut.co.tz/ | L50: Solar mini-grids and commercial solar solutions across Tanzania. | M50: Core fit: recurring field maintenance across many sites. Multi-location. | N50: Many remote sites and funder/lender reporting (DARES, AMDA etc.): GPS-verified O&M visits and photo evidence financiers trust. | O50: /demo?industry=solar&client=PowerHut%20Renewables%20Limited | P50: https://powerhut.co.tz/contact.html | Q50: Not contacted
A51: A | B51: Safi Power | C51: Solar | D51: C&I solar / EPC | E51: Kenya | F51: Nairobi | G51: sales@safi-power.com | H51: Company inbox | I51: +254 724 713 857 | J51: https://safi-power.com/ | K51: https://www.linkedin.com/company/safi-power/ | L51: Commercial and industrial solar company delivering renewable energy systems across Eastern Africa. | M51: Good fit: maintenance work across client sites. Multi-location. | N51: Turn one-off installs into recurring maintenance contracts: scheduled PM per site and client-facing service reports. | O51: /demo?industry=solar&client=Safi%20Power | P51: https://safi-power.com/ | Q51: Not contacted
A52: A | B52: Solar O&M South Africa | C52: Solar | D52: Solar O&M | E52: South Africa | F52: Johannesburg | G52: info@solar-om.co.za | H52: Company inbox | I52: 010 492 0558 | J52: https://www.solar-om.co.za/ | L52: O&M operator for utility solar plants (Lesedi, Letsatsi, Jasper and Greefspan II). | M52: Pure O&M operator for utility plants: core fit. | N52: O&M contracts depend on response time and proof of work: SLA tracking, verified site visits, client reports. | O52: /demo?industry=solar&client=Solar%20O%26M%20South%20Africa | P52: https://www.solar-om.co.za/ | Q52: Not contacted
A53: A | B53: Solareff | C53: Solar | D53: Solar O&M | E53: South Africa | F53: Roodepoort | G53: info@solareff.co.za | H53: Company inbox | I53: +27 11 675 1114 | J53: https://www.solareff.co.za/ | L53: South African renewable energy EPC with a dedicated solar operations and maintenance service. | M53: EPC with a dedicated O&M service. | N53: O&M contracts depend on response time and proof of work: SLA tracking, verified site visits, client reports. | O53: /demo?industry=solar&client=Solareff | P53: https://www.solareff.co.za/ | Q53: Not contacted
A54: A | B54: Wilkins Engineering Limited | C54: Solar | D54: C&I solar / EPC | E54: Ghana | F54: Accra | G54: info@wilkinsengineering.com | H54: Company inbox | I54: +233 30 223 5671 | J54: https://wilkinsengineering.com/ | K54: https://www.linkedin.com/company/wilkins-engineering-limited | L54: Solar and grid EPC contractor working in Ghana and across Africa. | M54: Good fit: maintenance work across client sites. Multi-location. | N54: Turn one-off installs into recurring maintenance contracts: scheduled PM per site and client-facing service reports. | O54: /demo?industry=solar&client=Wilkins%20Engineering%20Limited | P54: https://wilkinsengineering.com/ | Q54: Not contacted
A55: A | B55: Crest Technical Services | C55: Facility management | D55: Integrated FM | E55: Nigeria | F55: Lagos | H55: No email found | I55: 0803 302 3138 | J55: https://cresttechnicalservices.com/ | L55: Outsourcing and facilities management provider with offices in Lagos and Port Harcourt. | M55: Core fit: recurring field maintenance across many sites. Multi-location. | N55: Multi-building portfolio: planned maintenance schedules, technician dispatch and per-building client reporting. | O55: /demo?industry=facilities&client=Crest%20Technical%20Services | Q55: Not contacted
A56: A | B56: James Cubitt Facility Managers (JCFM) | C56: Facility management | D56: Integrated FM | E56: Nigeria | F56: Lagos | H56: No email found | J56: https://www.jamescubittfacilities.com/ | K56: https://ng.linkedin.com/company/james-cubitt-facilities-managers | L56: Facility management across the building lifecycle with offices in Ikoyi, Victoria Island and Lekki, plus on-call FM and concierge services. | M56: Core fit: recurring field maintenance across many sites. Multi-location. | N56: Multi-building portfolio: planned maintenance schedules, technician dispatch and per-building client reporting. | O56: /demo?industry=facilities&client=James%20Cubitt%20Facility%20Managers | Q56: Not contacted
A57: A | B57: ACOB Lighting Technology | C57: Solar | D57: Mini-grid developer/operator | E57: Nigeria | F57: Abuja | H57: No email found | J57: https://acoblighting.com | L57: Mini-grid developer and solar/LED streetlighting installer that also does energy audits for communities; IMAS grantee | M57: Core fit: recurring field maintenance across many sites. | N57: Many remote sites and funder/lender reporting (DARES, AMDA etc.): GPS-verified O&M visits and photo evidence financiers trust. | O57: /demo?industry=solar&client=ACOB%20Lighting%20Technology | Q57: Not contacted
A58: A | B58: Ashdam Solar Company Limited | C58: Solar | D58: Mini-grid developer/operator | E58: Nigeria | F58: Ibadan | H58: No email found | J58: https://ashdamsolar.com | K58: https://ng.linkedin.com/company/ashdamsolar | L58: Solar installations, inverter systems, energy consulting and training for homes, business and government; DARES mini-grid grantee | M58: Core fit: recurring field maintenance across many sites. | N58: Many remote sites and funder/lender reporting (DARES, AMDA etc.): GPS-verified O&M visits and photo evidence financiers trust. | O58: /demo?industry=solar&client=Ashdam%20Solar%20Company%20Limited | Q58: Not contacted
A59: A | B59: Ceesolar Energy Limited | C59: Solar | D59: Mini-grid developer/operator | E59: Nigeria | F59: Abuja | H59: No email found | J59: https://www.ceesolar.com | L59: Mini-grid development, commercial solar installations and energy consultancy | M59: Core fit: recurring field maintenance across many sites. | N59: Many remote sites and funder/lender reporting (DARES, AMDA etc.): GPS-verified O&M visits and photo evidence financiers trust. | O59: /demo?industry=solar&client=Ceesolar%20Energy%20Limited | Q59: Not contacted
A60: A | B60: GVE Projects (Green Village Electricity) | C60: Solar | D60: Mini-grid developer/operator | E60: Nigeria | F60: Abuja | H60: No email found | J60: https://gve-group.com | L60: Mini-grid developer (e.g. 1MW Wuse Market interconnected mini-grid) that also does residential and C&I solar; IMAS grantee | M60: Core fit: recurring field maintenance across many sites. | N60: Many remote sites and funder/lender reporting (DARES, AMDA etc.): GPS-verified O&M visits and photo evidence financiers trust. | O60: /demo?industry=solar&client=GVE%20Projects | Q60: Not contacted
A61: A | B61: MEP Erictric Technology Ltd | C61: Facility management | D61: Lifts & escalators | E61: Rwanda | F61: Kigali | H61: No email found | J61: https://meperictrictech.com/ | L61: MEP contractor (since 2016) that installs and maintains elevators, electrical systems, generators, plumbing and fire safety for buildings. | M61: Core fit: recurring field maintenance across many sites. | N61: Entrapment callouts and statutory inspections: response-time SLAs and inspection records per lift. | O61: /demo?industry=facilities&client=MEP%20Erictric%20Technology%20Ltd | Q61: Not contacted
A62: A | B62: Standard Microgrid | C62: Solar | D62: Mini-grid developer/operator | E62: Zambia | F62: Lusaka | H62: No email found | J62: https://standardmicrogrid.com/ | L62: Builds and operates rural solar microgrids in Zambia under operating rights from the Rural Electrification Authority. | M62: Core fit: recurring field maintenance across many sites. | N62: Many remote sites and funder/lender reporting (DARES, AMDA etc.): GPS-verified O&M visits and photo evidence financiers trust. | O62: /demo?industry=solar&client=Standard%20Microgrid | Q62: Not contacted
A63: B | B63: Audu Imonikhe & Co | C63: Facility management | D63: Property / estate FM | E63: Nigeria | F63: Port Harcourt | G63: auduimonikheandco@gmail.com | H63: Free-mail inbox | I63: 0803 370 7068 | J63: https://auduimonikheandco.com/ | L63: Facility and property management in Port Harcourt, including maintenance, utilities coordination and asset management. | M63: Good fit: maintenance work across client sites. | N63: Tenant requests become tracked work orders with technician dispatch and landlord reporting. | O63: /demo?industry=facilities&client=Audu%20Imonikhe%20%26%20Co | P63: https://auduimonikheandco.com/ | Q63: Not contacted
A64: B | B64: Betacool Engineering Limited | C64: Facility management | D64: HVAC maintenance | E64: Nigeria | F64: Lagos | G64: info@betacoolltd.com | H64: Company inbox | I64: +234 803 649 6114 | J64: https://betacoolltd.com/ | K64: https://www.linkedin.com/company/betacoolltd | L64: HVAC and ventilation design, installation and maintenance for residential, commercial and industrial clients. | M64: Good fit: maintenance work across client sites. | N64: Annual maintenance contracts: never miss a scheduled service, photo proof for every visit. | O64: /demo?industry=facilities&client=Betacool%20Engineering%20Limited | P64: https://betacoolltd.com/ | Q64: Not contacted
A65: B | B65: Bloom Projects and Facilities Management (Bloom PFM) | C65: Facility management | D65: Integrated FM | E65: Nigeria | F65: Lagos | G65: info@bloompfm.com | H65: Company inbox | I65: +234 814 400 0052 | J65: https://bloompfm.com/ | L65: Integrated FM with hard services (maintenance, technical operations) and soft services for commercial, residential and retail sites. | M65: Core fit: recurring field maintenance across many sites. | N65: Multi-building portfolio: planned maintenance schedules, technician dispatch and per-building client reporting. | O65: /demo?industry=facilities&client=Bloom%20Projects%20and%20Facilities%20Management | P65: https://bloompfm.com/ | Q65: Not contacted
A66: B | B66: Briscoe Properties Limited | C66: Facility management | D66: Property / estate FM | E66: Nigeria | F66: Lagos | G66: bpl@rtbriscoe.com | H66: Company inbox | I66: +234 707 475 4362 | J66: https://briscoeproperties.com/ | K66: https://ng.linkedin.com/company/briscoe-properties-limited | L66: Property management, facility management and engineering services (part of the R.T. Briscoe group). | M66: Good fit: maintenance work across client sites. | N66: Tenant requests become tracked work orders with technician dispatch and landlord reporting. | O66: /demo?industry=facilities&client=Briscoe%20Properties%20Limited | P66: https://briscoeproperties.com/ | Q66: Not contacted
A67: B | B67: Chrelect Limited | C67: Facility management | D67: MEP maintenance | E67: Nigeria | F67: Lagos | G67: info@chrelectmep.com | H67: Company inbox | I67: +234 916 537 2608 | J67: https://chrelectmep.com/ | L67: MEP, sprinkler and fire-protection engineering contractor with a maintenance workforce for long-term and one-off maintenance contracts. | M67: Good fit: maintenance work across client sites. | N67: Maintenance contracts across client buildings: work orders, checklists and proof of work per visit. | O67: /demo?industry=facilities&client=Chrelect%20Limited | P67: https://chrelectmep.com/ | Q67: Not contacted
A68: B | B68: Cxall Facilities & Management Services Limited | C68: Facility management | D68: Integrated FM | E68: Nigeria | F68: Lagos | G68: info@cxallng.com | H68: Company inbox | I68: +234 805 114 5531 | J68: https://cxallng.com/ | L68: Building maintenance, renovations, borehole drilling and smart technology installation for residential, commercial and industrial properties (Lagos and Abuja). | M68: Core fit: recurring field maintenance across many sites. | N68: Multi-building portfolio: planned maintenance schedules, technician dispatch and per-building client reporting. | O68: /demo?industry=facilities&client=Cxall%20Facilities%20%26%20Management%20Services%20Limited | P68: https://cxallng.com/ | Q68: Not contacted
A69: B | B69: Eko Maintenance Ltd | C69: Facility management | D69: Integrated FM | E69: Nigeria | F69: Lagos | G69: info@ekomaintenance.com | H69: Company inbox | I69: +234 807 627 5442 | J69: https://www.ekomaintenance.com/ | K69: https://www.linkedin.com/company/eko-maintenance-limited/ | L69: Facility and project management: operations, repairs, preventive maintenance and consultancy for buildings and infrastructure. | M69: Core fit: recurring field maintenance across many sites. | N69: Multi-building portfolio: planned maintenance schedules, technician dispatch and per-building client reporting. | O69: /demo?industry=facilities&client=Eko%20Maintenance%20Ltd | P69: https://www.ekomaintenance.com/ | Q69: Not contacted
A70: B | B70: Essential Facility Management | C70: Facility management | D70: Property / estate FM | E70: Nigeria | F70: Lagos | G70: info@essentialfacilitymgt.com | H70: Company inbox | I70: +234 806 603 0376 | J70: https://essentialfacilitymgt.com/ | L70: Property and estate facility management, security and project management in Lagos and Abuja. | M70: Good fit: maintenance work across client sites. | N70: Tenant requests become tracked work orders with technician dispatch and landlord reporting. | O70: /demo?industry=facilities&client=Essential%20Facility%20Management | P70: https://essentialfacilitymgt.com/ | Q70: Not contacted
A71: B | B71: Green Facilities Limited | C71: Facility management | D71: Integrated FM | E71: Nigeria | F71: Lagos | G71: info@greenfacilitiesltd.com | H71: Company inbox | I71: +234 809 065 0913 | J71: https://greenfacilitiesltd.com/ | K71: https://www.linkedin.com/company/greenfacltd/ | L71: Victoria Island facility management firm focused on efficiency and sustainability in FM. | M71: Core fit: recurring field maintenance across many sites. | N71: Multi-building portfolio: planned maintenance schedules, technician dispatch and per-building client reporting. | O71: /demo?industry=facilities&client=Green%20Facilities%20Limited | P71: https://greenfacilitiesltd.com/ | Q71: Not contacted
A72: B | B72: GreenBox Facilities Limited | C72: Facility management | D72: MEP maintenance | E72: Nigeria | F72: Abuja | G72: info@greenboxfacilities.com | H72: Company inbox | I72: +234 817 204 7533 | J72: https://greenboxfacilities.com/ | L72: Technology-driven FM in Abuja, including general MEP, carpentry and civil maintenance, cleaning and pest control. | M72: Good fit: maintenance work across client sites. | N72: Maintenance contracts across client buildings: work orders, checklists and proof of work per visit. | O72: /demo?industry=facilities&client=GreenBox%20Facilities%20Limited | P72: https://greenboxfacilities.com/ | Q72: Not contacted
A73: B | B73: IKON Facilities Limited | C73: Facility management | D73: Integrated FM | E73: Nigeria | F73: Abuja | G73: info@ikonfacilities.com | H73: Company inbox | I73: +234 908 664 4446 | J73: https://ikonfacilities.com/ | K73: https://www.linkedin.com/company/ikon-facilities/ | L73: Fully integrated FM: maintenance, cleaning, security, utilities management and HSE consulting. | M73: Core fit: recurring field maintenance across many sites. | N73: Multi-building portfolio: planned maintenance schedules, technician dispatch and per-building client reporting. | O73: /demo?industry=facilities&client=IKON%20Facilities%20Limited | P73: https://ikonfacilities.com/ | Q73: Not contacted
A74: B | B74: Marvel Homes Property Management | C74: Facility management | D74: Property / estate FM | E74: Nigeria | F74: Lagos | G74: info@marvelhomespm.com | H74: Company inbox | I74: +234 916 232 3655 | J74: https://www.marvelhomespm.com/ | L74: Corporate facility management and property maintenance services across Lagos. | M74: Good fit: maintenance work across client sites. | N74: Tenant requests become tracked work orders with technician dispatch and landlord reporting. | O74: /demo?industry=facilities&client=Marvel%20Homes%20Property%20Management | P74: https://www.marvelhomespm.com/ | Q74: Not contacted
A75: B | B75: Max-Migold Ltd | C75: Facility management | D75: Integrated FM | E75: Nigeria | F75: Lagos | G75: info@maxmigold.com | H75: Company inbox | I75: +234 802 202 0122 | J75: https://maxmigold.com/ | L75: Facility management operations, energy management, smart building systems, asset advisory and FM training. | M75: Core fit: recurring field maintenance across many sites. | N75: Multi-building portfolio: planned maintenance schedules, technician dispatch and per-building client reporting. | O75: /demo?industry=facilities&client=Max-Migold%20Ltd | P75: https://maxmigold.com/ | Q75: Not contacted
A76: B | B76: Mosaic Management Ltd | C76: Facility management | D76: Integrated FM | E76: Nigeria | F76: Lagos | G76: info@mosaicmanagementltd.com | H76: Company inbox | I76: +234 700 667 7790 | J76: https://mosaicmanagementltd.com/ | L76: Integrated infrastructure solutions: real estate/facility services, hygiene, operational risk management and capital project delivery. | M76: Core fit: recurring field maintenance across many sites. | N76: Multi-building portfolio: planned maintenance schedules, technician dispatch and per-building client reporting. | O76: /demo?industry=facilities&client=Mosaic%20Management%20Ltd | P76: https://mosaicmanagementltd.com/ | Q76: Not contacted
A77: B | B77: Oviswift Engineering & Consultancy Limited | C77: Facility management | D77: Integrated FM | E77: Nigeria | F77: Abuja | G77: contact@oviswift.com | H77: Company inbox | I77: +234 807 040 0500 | J77: https://oviswift.com/ | K77: https://www.linkedin.com/company/oviswift-enigineering-consultancy-limited/ | L77: FM covering technical maintenance, janitorial, gardening, pest control and waste services, plus engineering and oil and gas consultancy. | M77: Core fit: recurring field maintenance across many sites. | N77: Multi-building portfolio: planned maintenance schedules, technician dispatch and per-building client reporting. | O77: /demo?industry=facilities&client=Oviswift%20Engineering%20%26%20Consultancy%20Limited | P77: https://oviswift.com/ | Q77: Not contacted
A78: B | B78: PrimeCool Tech Ltd | C78: Facility management | D78: HVAC maintenance | E78: Nigeria | F78: Lagos | G78: primecooltech.ng@gmail.com | H78: Free-mail inbox | I78: +234 802 647 1785 | J78: https://primecooltech.ng/ | L78: HVAC installation, repair and maintenance for residential and commercial properties, with a 24/7 emergency service. | M78: Good fit: maintenance work across client sites. | N78: Annual maintenance contracts: never miss a scheduled service, photo proof for every visit. | O78: /demo?industry=facilities&client=PrimeCool%20Tech%20Ltd | P78: https://primecooltech.ng/ | Q78: Not contacted
A79: B | B79: Principal Facilities Management Limited (PFML) | C79: Facility management | D79: Integrated FM | E79: Nigeria | F79: Abuja | G79: info@principalfml.com | H79: Company inbox | I79: +234 904 937 1010 | J79: https://principalfml.com/ | K79: https://www.linkedin.com/company/principal-fml | L79: Integrated FM with technical operations and maintenance, management services and advisory for residential and commercial properties in Abuja and Lagos. | M79: Core fit: recurring field maintenance across many sites. | N79: Multi-building portfolio: planned maintenance schedules, technician dispatch and per-building client reporting. | O79: /demo?industry=facilities&client=Principal%20Facilities%20Management%20Limited | P79: https://principalfml.com/ | Q79: Not contacted
A80: B | B80: Provast Limited | C80: Facility management | D80: Integrated FM | E80: Nigeria | F80: Lagos | G80: info@provastltd.com | H80: Company inbox | I80: +234 818 070 2290 | J80: https://provastltd.com/ | K80: https://www.linkedin.com/company/provast-limited/ | L80: Integrated facility management, building maintenance, MEP works, renovation and property management across Lagos. | M80: Core fit: recurring field maintenance across many sites. | N80: Multi-building portfolio: planned maintenance schedules, technician dispatch and per-building client reporting. | O80: /demo?industry=facilities&client=Provast%20Limited | P80: https://provastltd.com/ | Q80: Not contacted
A81: B | B81: Prysm Facility Services Limited | C81: Facility management | D81: Integrated FM | E81: Nigeria | F81: Lagos | G81: info@prysmfacilities.com | H81: Company inbox | J81: https://prysmfacilities.com/ | L81: Integrated FM in Nigeria covering cleaning, maintenance, security, HVAC and project management. | M81: Core fit: recurring field maintenance across many sites. | N81: Multi-building portfolio: planned maintenance schedules, technician dispatch and per-building client reporting. | O81: /demo?industry=facilities&client=Prysm%20Facility%20Services%20Limited | P81: https://prysmfacilities.com/ | Q81: Not contacted
A82: B | B82: RP Facilities Limited | C82: Facility management | D82: Integrated FM | E82: Nigeria | F82: Lagos | G82: business.rpfacilities@gmail.com | H82: Free-mail inbox | I82: +234 808 585 4001 | J82: https://www.rpfacilities.com/ | K82: https://www.linkedin.com/company/rp-facilities-management/ | L82: Facility management plus water treatment, reverse osmosis and sewage treatment plant services for commercial, healthcare, school and government buildings. | M82: Core fit: recurring field maintenance across many sites. | N82: Multi-building portfolio: planned maintenance schedules, technician dispatch and per-building client reporting. | O82: /demo?industry=facilities&client=RP%20Facilities%20Limited | P82: https://www.rpfacilities.com/ | Q82: Not contacted
A83: B | B83: Rhapsody FM (AOC Real Estate Group) | C83: Facility management | D83: Integrated FM | E83: Nigeria | F83: Lagos | G83: info@aoc-group.net | H83: Company inbox | I83: +234 818 125 1091 | J83: https://rhapsodyfm.com/ | K83: https://www.linkedin.com/company/aoc-real-estate-group/ | L83: Integrated FM including property and tenant management, manpower and project management. | M83: Core fit: recurring field maintenance across many sites. | N83: Multi-building portfolio: planned maintenance schedules, technician dispatch and per-building client reporting. | O83: /demo?industry=facilities&client=Rhapsody%20FM | P83: https://rhapsodyfm.com/ | Q83: Not contacted
A84: B | B84: SolidEdge Facilities Services Limited | C84: Facility management | D84: Integrated FM | E84: Nigeria | F84: Lagos | G84: helpdesk@sefacilities.com | H84: Company inbox | I84: +234 703 224 0195 | J84: https://sefacilities.com/ | L84: Technical and non-technical FM and maintenance services for corporate organisations. | M84: Core fit: recurring field maintenance across many sites. | N84: Multi-building portfolio: planned maintenance schedules, technician dispatch and per-building client reporting. | O84: /demo?industry=facilities&client=SolidEdge%20Facilities%20Services%20Limited | P84: https://sefacilities.com/ | Q84: Not contacted
A85: B | B85: Total Facilities Management Limited (TFML) | C85: Facility management | D85: Integrated FM | E85: Nigeria | F85: Abuja | G85: info@tfmlconsultant.com | H85: Company inbox | I85: +234 701 023 5555 | J85: https://www.tfmlconsultant.com/ | K85: https://ng.linkedin.com/company/tfml | L85: ISO-certified integrated FM provider with operations in Abuja, Lagos and Enugu. | M85: Core fit: recurring field maintenance across many sites. | N85: Multi-building portfolio: planned maintenance schedules, technician dispatch and per-building client reporting. | O85: /demo?industry=facilities&client=Total%20Facilities%20Management%20Limited | P85: https://www.tfmlconsultant.com/ | Q85: Not contacted
A86: B | B86: UPDC Facility Management Ltd (UPDCFM) | C86: Facility management | D86: Integrated FM | E86: Nigeria | F86: Lagos | G86: info@updcfm.com | H86: Company inbox | I86: +234 901 000 3020 | J86: https://updcfm.com/ | K86: https://www.linkedin.com/company/updc-facility-management-limited/ | L86: Management, maintenance and sustainable power solutions for residential, corporate and commercial properties. | M86: Core fit: recurring field maintenance across many sites. | N86: Multi-building portfolio: planned maintenance schedules, technician dispatch and per-building client reporting. | O86: /demo?industry=facilities&client=UPDC%20Facility%20Management%20Ltd | P86: https://updcfm.com/ | Q86: Not contacted
A87: B | B87: Alexoll Energy Solutions | C87: Solar | D87: C&I solar / EPC | E87: Nigeria | F87: Port Harcourt | G87: info@alexoll.com | H87: Company inbox | I87: +2349157683237 | J87: https://alexoll.com | L87: Residential and commercial solar installer in Port Harcourt (claims 3MW+ generated) | M87: Good fit: maintenance work across client sites. | N87: Turn one-off installs into recurring maintenance contracts: scheduled PM per site and client-facing service reports. | O87: /demo?industry=solar&client=Alexoll%20Energy%20Solutions | P87: https://alexoll.com | Q87: Not contacted
A88: B | B88: Eauxwell Nigeria | C88: Solar | D88: C&I solar / EPC | E88: Nigeria | F88: Lagos | G88: info@eauxwell.com | H88: Company inbox | J88: https://eauxwell.com | L88: Solar EPC with 120MW+ deployed (rooftop, utility-scale and BESS), plus water engineering | M88: Good fit: maintenance work across client sites. | N88: Turn one-off installs into recurring maintenance contracts: scheduled PM per site and client-facing service reports. | O88: /demo?industry=solar&client=Eauxwell%20Nigeria | P88: https://eauxwell.com | Q88: Not contacted
A89: B | B89: Gennex Technologies | C89: Solar | D89: Residential & small commercial installer | E89: Nigeria | F89: Lagos | G89: customercare@gennextechnologies.com | H89: Company inbox | I89: 02012934490 | J89: https://gennextechnologies.com | K89: https://www.linkedin.com/company/gennextechnologies/ | L89: Solar sales, distribution and installation with offices in Lekki (HQ) and Abuja | M89: Smaller jobs; fit depends on service volume. Multi-location. | N89: High volume of service calls across many homes: dispatch the nearest technician and track repeat faults. | O89: /demo?industry=solar&client=Gennex%20Technologies | P89: https://gennextechnologies.com/contact-us/ | Q89: Not contacted
A90: B | B90: HakunaSolar | C90: Solar | D90: C&I solar / EPC | E90: Nigeria | F90: Port Harcourt | G90: Info@hakunasolar.com | H90: Company inbox | I90: +234 803 8341853 | J90: https://hakunasolar.com | L90: Residential and industrial solar/hybrid installer claiming 2,500+ installations | M90: Good fit: maintenance work across client sites. | N90: Turn one-off installs into recurring maintenance contracts: scheduled PM per site and client-facing service reports. | O90: /demo?industry=solar&client=HakunaSolar | P90: https://hakunasolar.com | Q90: Not contacted
A91: B | B91: Solar Force Nigeria | C91: Solar | D91: C&I solar / EPC | E91: Nigeria | F91: Abuja | G91: info@solarforcenigeria.com | H91: Company inbox | I91: +234 8172 889 357 | J91: https://www.solarforcenigeria.com | K91: https://ng.linkedin.com/company/solarforce-nigeria-ltd | L91: Solar EPC for utility-scale and C&I solar and storage projects | M91: Good fit: maintenance work across client sites. | N91: Turn one-off installs into recurring maintenance contracts: scheduled PM per site and client-facing service reports. | O91: /demo?industry=solar&client=Solar%20Force%20Nigeria | P91: https://www.solarforcenigeria.com | Q91: Not contacted
A92: B | B92: Bestcare Facilities Management Services | C92: Facility management | D92: Integrated FM | E92: Kenya | F92: Nairobi | G92: info@bestcareservices.co.ke | H92: Company inbox | I92: 0722566999 | J92: https://bestcareservices.co.ke/ | L92: Integrated FM and maintenance provider doing HVAC, electrical, plumbing and preventive maintenance alongside cleaning and security. | M92: Core fit: recurring field maintenance across many sites. | N92: Multi-building portfolio: planned maintenance schedules, technician dispatch and per-building client reporting. | O92: /demo?industry=facilities&client=Bestcare%20Facilities%20Management%20Services | P92: https://bestcareservices.co.ke/ | Q92: Not contacted
A93: B | B93: C & C Facilities Management | C93: Facility management | D93: Property / estate FM | E93: Ghana | F93: Accra | G93: ccfm@chezo.africa | H93: Company inbox | I93: 0245469694 | J93: https://cleaning.chezo.africa/ | L93: Facility partner for corporate clients covering property maintenance, generator/UPS/solar management, janitorial, pest control and landscaping. | M93: Good fit: maintenance work across client sites. | N93: Tenant requests become tracked work orders with technician dispatch and landlord reporting. | O93: /demo?industry=facilities&client=C%20%26%20C%20Facilities%20Management | P93: https://cleaning.chezo.africa/ | Q93: Not contacted
A94: B | B94: CYUSA Technology Africa | C94: Facility management | D94: HVAC maintenance | E94: Rwanda | F94: Kigali | G94: info@cyusatech.com | H94: Company inbox | I94: +250 788621795 | J94: https://cyusatech.com/ | L94: MEP, HVAC and fire-safety provider offering MEP maintenance contracts, preventive HVAC maintenance and fire-suppression servicing. | M94: Good fit: maintenance work across client sites. | N94: Annual maintenance contracts: never miss a scheduled service, photo proof for every visit. | O94: /demo?industry=facilities&client=CYUSA%20Technology%20Africa | P94: https://cyusatech.com/contact-us/ | Q94: Not contacted
A95: B | B95: Depriss Facilities Management (Depriss Group) | C95: Facility management | D95: Integrated FM | E95: Kenya | F95: Nairobi | G95: info@deprissgrp.co.ke | H95: Company inbox | I95: +254 711 207 777 | J95: https://deprissgrp.co.ke/ | K95: https://www.linkedin.com/company/deprissifm | L95: Integrated FM provider offering hard and soft services, property oversight and project coordination for residential and commercial clients. | M95: Core fit: recurring field maintenance across many sites. | N95: Multi-building portfolio: planned maintenance schedules, technician dispatch and per-building client reporting. | O95: /demo?industry=facilities&client=Depriss%20Facilities%20Management | P95: https://deprissgrp.co.ke/ | Q95: Not contacted
A96: B | B96: Emdad Facility Management | C96: Facility management | D96: Integrated FM | E96: Egypt | F96: New Cairo | G96: info@emdad-fm.com | H96: Company inbox | I96: +2 02 230 67 297 | J96: https://emdad-fm.com/ | L96: Egyptian-owned integrated FM provider doing MEP and building maintenance, landscaping, cleaning and pest control for residential and commercial sites. | M96: Core fit: recurring field maintenance across many sites. | N96: Multi-building portfolio: planned maintenance schedules, technician dispatch and per-building client reporting. | O96: /demo?industry=facilities&client=Emdad%20Facility%20Management | P96: https://emdad-fm.com/ | Q96: Not contacted
A97: B | B97: ExperTech FM | C97: Facility management | D97: MEP maintenance | E97: Egypt | F97: Giza (6th of October) | G97: info@expertech-eg.com | H97: Company inbox | I97: +2 010 14 0000 25 | J97: https://expertech-eg.com/ | K97: http://www.linkedin.com/company/expertecheg | L97: FM provider delivering hard services and MEP maintenance for all types of properties. | M97: Good fit: maintenance work across client sites. | N97: Maintenance contracts across client buildings: work orders, checklists and proof of work per visit. | O97: /demo?industry=facilities&client=ExperTech%20FM | P97: https://expertech-eg.com/ | Q97: Not contacted
A98: B | B98: Fides Group | C98: Facility management | D98: Integrated FM | E98: Ghana | F98: Accra | G98: info@fidesgroupgh.com | H98: Company inbox | I98: +233 54 0131 789 | J98: https://www.fidesgroupgh.com/ | K98: https://www.linkedin.com/in/fides-group-4a14a7160/ | L98: Integrated facility management and property management firm helping organisations optimise building operations. | M98: Core fit: recurring field maintenance across many sites. | N98: Multi-building portfolio: planned maintenance schedules, technician dispatch and per-building client reporting. | O98: /demo?industry=facilities&client=Fides%20Group | P98: https://www.fidesgroupgh.com/ | Q98: Not contacted
A99: B | B99: GNA Real Estate | C99: Facility management | D99: Integrated FM | E99: Kenya | F99: Nairobi | G99: support@gna.co.ke | H99: Company inbox | I99: +254 712 406 060 | J99: https://gna.co.ke/ | K99: https://www.linkedin.com/company/gnarealestate/about/ | L99: Real estate firm offering integrated hard and soft FM, including building maintenance, security, landscaping and waste management. | M99: Core fit: recurring field maintenance across many sites. | N99: Multi-building portfolio: planned maintenance schedules, technician dispatch and per-building client reporting. | O99: /demo?industry=facilities&client=GNA%20Real%20Estate | P99: https://gna.co.ke/ | Q99: Not contacted
A100: B | B100: Green Space Ltd | C100: Facility management | D100: Integrated FM | E100: Rwanda | F100: Kigali | G100: tunga@greenspace.rw | H100: Named person | I100: +250 788 312 238 | J100: https://greenspace.rw/ | L100: Project management, infrastructure development and facility management company covering landscaping, building and maintenance. | M100: Core fit: recurring field maintenance across many sites. | N100: Multi-building portfolio: planned maintenance schedules, technician dispatch and per-building client reporting. | O100: /demo?industry=facilities&client=Green%20Space%20Ltd | P100: https://greenspace.rw/ | Q100: Not contacted
...

Sheet Summary
A1: Lead list summary
A2: All counts are live formulas over the Leads tab.
A4: Country | B4: Solar | C4: Facility mgmt | D4: Total | E4: With email | F4: Priority A
A5: Nigeria | B5: =COUNTIFS(Leads!$E$2:$E$161,$A5,Leads!$C$2:$C$161,"Solar") -> 40 | C5: =COUNTIFS(Leads!$E$2:$E$161,$A5,Leads!$C$2:$C$161,"Facility management") -> 40 | D5: =B5+C5 -> 80 | E5: =COUNTIFS(Leads!$E$2:$E$161,$A5,Leads!$G$2:$G$161,"<>") -> 67 | F5: =COUNTIFS(Leads!$E$2:$E$161,$A5,Leads!$A$2:$A$161,"A") -> 32
A6: Egypt | B6: =COUNTIFS(Leads!$E$2:$E$161,$A6,Leads!$C$2:$C$161,"Solar") -> 0 | C6: =COUNTIFS(Leads!$E$2:$E$161,$A6,Leads!$C$2:$C$161,"Facility management") -> 7 | D6: =B6+C6 -> 7 | E6: =COUNTIFS(Leads!$E$2:$E$161,$A6,Leads!$G$2:$G$161,"<>") -> 6 | F6: =COUNTIFS(Leads!$E$2:$E$161,$A6,Leads!$A$2:$A$161,"A") -> 1
A7: Ghana | B7: =COUNTIFS(Leads!$E$2:$E$161,$A7,Leads!$C$2:$C$161,"Solar") -> 6 | C7: =COUNTIFS(Leads!$E$2:$E$161,$A7,Leads!$C$2:$C$161,"Facility management") -> 9 | D7: =B7+C7 -> 15 | E7: =COUNTIFS(Leads!$E$2:$E$161,$A7,Leads!$G$2:$G$161,"<>") -> 14 | F7: =COUNTIFS(Leads!$E$2:$E$161,$A7,Leads!$A$2:$A$161,"A") -> 4
A8: Kenya | B8: =COUNTIFS(Leads!$E$2:$E$161,$A8,Leads!$C$2:$C$161,"Solar") -> 10 | C8: =COUNTIFS(Leads!$E$2:$E$161,$A8,Leads!$C$2:$C$161,"Facility management") -> 8 | D8: =B8+C8 -> 18 | E8: =COUNTIFS(Leads!$E$2:$E$161,$A8,Leads!$G$2:$G$161,"<>") -> 18 | F8: =COUNTIFS(Leads!$E$2:$E$161,$A8,Leads!$A$2:$A$161,"A") -> 5
A9: Morocco | B9: =COUNTIFS(Leads!$E$2:$E$161,$A9,Leads!$C$2:$C$161,"Solar") -> 0 | C9: =COUNTIFS(Leads!$E$2:$E$161,$A9,Leads!$C$2:$C$161,"Facility management") -> 2 | D9: =B9+C9 -> 2 | E9: =COUNTIFS(Leads!$E$2:$E$161,$A9,Leads!$G$2:$G$161,"<>") -> 1 | F9: =COUNTIFS(Leads!$E$2:$E$161,$A9,Leads!$A$2:$A$161,"A") -> 0
A10: Rwanda | B10: =COUNTIFS(Leads!$E$2:$E$161,$A10,Leads!$C$2:$C$161,"Solar") -> 2 | C10: =COUNTIFS(Leads!$E$2:$E$161,$A10,Leads!$C$2:$C$161,"Facility management") -> 3 | D10: =B10+C10 -> 5 | E10: =COUNTIFS(Leads!$E$2:$E$161,$A10,Leads!$G$2:$G$161,"<>") -> 3 | F10: =COUNTIFS(Leads!$E$2:$E$161,$A10,Leads!$A$2:$A$161,"A") -> 2
A11: South Africa | B11: =COUNTIFS(Leads!$E$2:$E$161,$A11,Leads!$C$2:$C$161,"Solar") -> 14 | C11: =COUNTIFS(Leads!$E$2:$E$161,$A11,Leads!$C$2:$C$161,"Facility management") -> 8 | D11: =B11+C11 -> 22 | E11: =COUNTIFS(Leads!$E$2:$E$161,$A11,Leads!$G$2:$G$161,"<>") -> 20 | F11: =COUNTIFS(Leads!$E$2:$E$161,$A11,Leads!$A$2:$A$161,"A") -> 11
A12: Tanzania | B12: =COUNTIFS(Leads!$E$2:$E$161,$A12,Leads!$C$2:$C$161,"Solar") -> 4 | C12: =COUNTIFS(Leads!$E$2:$E$161,$A12,Leads!$C$2:$C$161,"Facility management") -> 2 | D12: =B12+C12 -> 6 | E12: =COUNTIFS(Leads!$E$2:$E$161,$A12,Leads!$G$2:$G$161,"<>") -> 6 | F12: =COUNTIFS(Leads!$E$2:$E$161,$A12,Leads!$A$2:$A$161,"A") -> 4
A13: Uganda | B13: =COUNTIFS(Leads!$E$2:$E$161,$A13,Leads!$C$2:$C$161,"Solar") -> 2 | C13: =COUNTIFS(Leads!$E$2:$E$161,$A13,Leads!$C$2:$C$161,"Facility management") -> 1 | D13: =B13+C13 -> 3 | E13: =COUNTIFS(Leads!$E$2:$E$161,$A13,Leads!$G$2:$G$161,"<>") -> 2 | F13: =COUNTIFS(Leads!$E$2:$E$161,$A13,Leads!$A$2:$A$161,"A") -> 0
A14: Zambia | B14: =COUNTIFS(Leads!$E$2:$E$161,$A14,Leads!$C$2:$C$161,"Solar") -> 2 | C14: =COUNTIFS(Leads!$E$2:$E$161,$A14,Leads!$C$2:$C$161,"Facility management") -> 0 | D14: =B14+C14 -> 2 | E14: =COUNTIFS(Leads!$E$2:$E$161,$A14,Leads!$G$2:$G$161,"<>") -> 1 | F14: =COUNTIFS(Leads!$E$2:$E$161,$A14,Leads!$A$2:$A$161,"A") -> 2
A15: Total | B15: =SUM(B5:B14) -> 80 | C15: =SUM(C5:C14) -> 80 | D15: =SUM(D5:D14) -> 160 | E15: =SUM(E5:E14) -> 138 | F15: =SUM(F5:F14) -> 61
A17: Priority | B17: Leads | C17: With email | D17: Meaning
A18: A | B18: =COUNTIF(Leads!$A$2:$A$161,A18) -> 61 | C18: =COUNTIFS(Leads!$A$2:$A$161,A18,Leads!$G$2:$G$161,"<>") -> 53 | D18: Core fit: recurring field maintenance across many sites. Start here.
A19: B | B19: =COUNTIF(Leads!$A$2:$A$161,A19) -> 79 | C19: =COUNTIFS(Leads!$A$2:$A$161,A19,Leads!$G$2:$G$161,"<>") -> 69 | D19: Good fit; qualify on a call.
A20: C | B20: =COUNTIF(Leads!$A$2:$A$161,A20) -> 20 | C20: =COUNTIFS(Leads!$A$2:$A$161,A20,Leads!$G$2:$G$161,"<>") -> 16 | D20: Weaker fit (very large, in-house tech, or mostly product sales).
A22: Outreach status | B22: Count
A23: Not contacted | B23: =COUNTIF(Leads!$Q$2:$Q$161,A23) -> 160
A24: Sent | B24: =COUNTIF(Leads!$Q$2:$Q$161,A24) -> 0
A25: Follow-up 1 sent | B25: =COUNTIF(Leads!$Q$2:$Q$161,A25) -> 0
A26: Follow-up 2 sent | B26: =COUNTIF(Leads!$Q$2:$Q$161,A26) -> 0
A27: Replied | B27: =COUNTIF(Leads!$Q$2:$Q$161,A27) -> 0
A28: Meeting booked | B28: =COUNTIF(Leads!$Q$2:$Q$161,A28) -> 0
A29: Not interested | B29: =COUNTIF(Leads!$Q$2:$Q$161,A29) -> 0
A30: Bounced | B30: =COUNTIF(Leads!$Q$2:$Q$161,A30) -> 0

Sheet Email templates
A1: Cold email templates
A2: Replace {{Company}}, {{FirstName}} and {{DemoLink}} (your demo URL + the row's demo link path). Keep it plain text, one link, no attachments.
A4: Segment | B4: Step | C4: Subject / body
A5: Solar & mini-grids | B5: Email 1 (day 0) | C5: Subject: {{Company}}'s field team Hi {{FirstName}}, When a company runs installations or mini-grids across many sites, maintenance usually lives in WhatsApp groups and spreadsheets. Then a client, lender or funder asks for proof of O&M and someone spends a week pulling it together. We build custom field-operations software for energy companies: jobs sent to technicians' phones, GPS-verified site check-ins, time-stamped photo inspections, and a live view of every asset. I set up a short demo with {{Company}}'s name on it. It shows a technician reporting an inverter fault and the ops team dispatching a fix: {{DemoLink}} Would a 20-minute call to see if it fits how your team works be useful? Perfection Loveday Opensaucery
A6: Solar & mini-grids | B6: Follow-up 1 (day 3–4) | C6: Subject: Re: {{Company}}'s field team Hi {{FirstName}}, one detail that tends to matter to operators: every site visit is logged with GPS and photos taken in the app, so you can show exactly when each asset was last serviced, and what was found, without chasing anyone. The demo is here if you'd like a look: {{DemoLink}} Perfection
A7: Solar & mini-grids | B7: Follow-up 2 (day 8–10) | C7: Subject: Close the loop? Hi {{FirstName}}, I'll stop here so I'm not cluttering your inbox. If tracking maintenance across your sites becomes a priority later, just reply to this email and I'll send over a version built around your actual sites and equipment. Perfection
A8: Facility management | B8: Email 1 (day 0) | C8: Subject: Maintenance across {{Company}}'s buildings Hi {{FirstName}}, FM teams running chillers, lifts, generators and PPM schedules across many buildings often juggle job cards, calls and spreadsheets. Then a client asks for proof that a visit happened. We build custom maintenance and field-operations software: work orders sent to engineers' phones, GPS-verified check-ins, photo-stamped checklists, planned maintenance schedules and a live dashboard per building. I set up a short demo with {{Company}}'s name on it. It shows a chiller trip being reported and an engineer dispatched in under a minute: {{DemoLink}} Would a 20-minute call be worth it to see if it fits how you work? Perfection Loveday Opensaucery
A9: Facility management | B9: Follow-up 1 (day 3–4) | C9: Subject: Re: Maintenance across {{Company}}'s buildings Hi {{FirstName}}, one thing FM clients tend to value: every visit comes with GPS proof and photos, and the client report writes itself at month-end. No more rebuilding it from job cards. Demo: {{DemoLink}} Perfection
A10: Facility management | B10: Follow-up 2 (day 8–10) | C10: Subject: Close the loop? Hi {{FirstName}}, I'll leave it here. If digitising maintenance across your portfolio comes up later, reply and I'll put together a version using your buildings and equipment. Perfection

Sheet How this was built
A1: How this list was built
A2: • Companies found by web research (industry lists, association and funder programme lists like DARES/IMAS/AMDA, and company websites) on 22 Sept 2026.
A3: • Every email and phone was read from the company's own website or a public listing. Nothing was guessed or generated. The source is in the 'Email source' column.
A4: • Apify was not used: the account did not have enough credit this billing cycle.
A6: Before you send
A7: • Emails were NOT verified with a mail-server check. Run the list through a verifier (e.g. NeverBounce, ZeroBounce, or Apify email verification once topped up) to avoid bounces hurting your domain.
A8: • Most addresses are company inboxes (info@, sales@). Where you can, find the operations or maintenance lead on LinkedIn and address them by name.
A9: • Send from a secondary domain (e.g. opensaucery-mail.com) warmed up for 2–3 weeks, 20–30 emails/day to start.
A10: • Include who you are, a real postal address and a one-line opt-out. Honour opt-outs. Nigeria (NDPA), Kenya (Data Protection Act), South Africa (POPIA) and Ghana all have data-protection rules on marketing; B2B cold email to company inboxes is generally low-risk if you stay honest and let people opt out. This is not legal advice.
A12: Demo links
A13: • The 'Demo link path' column opens the FieldOps demo pre-branded with the company's name. Deploy the dashboard, then prefix each path with your URL, e.g. https://demo.opensaucery.africa/demo?industry=solar&client=Havenhill%20Synergy.
